{
  "id": "main_overons",
  "type": "SharedSlice",
  "name": "MainOverons",
  "description": "MainOverons",
  "variations": [
    {
      "id": "default",
      "name": "Default",
      "docURL": "...",
      "version": "initial",
      "description": "Default",
      "imageUrl": "",
      "primary": {
        "title": {
          "type": "Text",
          "config": {
            "label": "title",
            "placeholder": ""
          }
        },
        "subtitle": {
          "type": "Text",
          "config": {
            "label": "subtitle",
            "placeholder": ""
          }
        }
      },
      "items": {
        "membername": {
          "type": "Text",
          "config": {
            "label": "memberName",
            "placeholder": ""
          }
        },
        "memberimg": {
          "type": "Image",
          "config": {
            "label": "memberImg",
            "constraint": {},
            "thumbnails": []
          }
        },
        "githublink": {
          "type": "Link",
          "config": {
            "label": "githubLink",
            "placeholder": "",
            "select": null
          }
        }
      }
    }
  ]
}